corker-0.5.0.dist-info/top_level.txt
corker-0.5.0.dist-info/metadata.json
corker-0.5.0.dist-info/pbr.json
corker-0.5.0.dist-info/WHEEL
corker-0.5.0.dist-info/RECORD
corker-0.5.0.dist-info/METADATA
corker-0.5.0.dist-info/DESCRIPTION.rst
corker/__init__.py
corker/app.py
corker/controller.py
corker/tests/test_controller.py
corker/tests/test_main.py
corker/tests/__init__.py
