Metadata-Version: 2.0
Name: corker
Version: 0.5.0
Summary: Another WSGI Framework
Home-page: https://github.com/jd-boyd/corker
Author: Joshua D. Boyd
Author-email: jdboyd@jdboyd.net
License: BSD
Platform: UNKNOWN
Classifier: Development Status :: 4 - Beta
Classifier: Intended Audience :: Developers
Classifier: License :: OSI Approved :: BSD License
Classifier: Topic :: Internet :: WWW/HTTP
Classifier: Topic :: Software Development :: Libraries :: Python Modules
Classifier: Programming Language :: Python
Classifier: Programming Language :: Python :: 2
Classifier: Programming Language :: Python :: 2.7
Classifier: Programming Language :: Python :: 3
Classifier: Programming Language :: Python :: 3.3
Classifier: Programming Language :: Python :: 3.4
Requires-Dist: webob
Requires-Dist: routes
